ln_io_python/__init__.py
ln_io_python/in_function.py
ln_io_python/in_python.py
ln_io_python/out_python.py
LN_IO_Python-1.0.0.dist-info/AUTHORS.rst
LN_IO_Python-1.0.0.dist-info/LICENSE
LN_IO_Python-1.0.0.dist-info/METADATA
LN_IO_Python-1.0.0.dist-info/WHEEL
LN_IO_Python-1.0.0.dist-info/entry_points.txt
LN_IO_Python-1.0.0.dist-info/top_level.txt
LN_IO_Python-1.0.0.dist-info/zip-safe
LN_IO_Python-1.0.0.dist-info/RECORD
